autopy-4.0.1.dist-info/METADATA
autopy-4.0.1.dist-info/WHEEL
autopy-4.0.1.dist-info/licenses/LICENSE-APACHE
autopy-4.0.1.dist-info/licenses/LICENSE-MIT
autopy/__init__.py
autopy/autopy.cpython-311-darwin.so
autopy-4.0.1.dist-info/RECORD
