Metadata-Version: 2.4
Name: autopy
Version: 4.0.1
Classifier: Programming Language :: Rust
Classifier: Programming Language :: Python :: Implementation :: CPython
Classifier: Programming Language :: Python :: Implementation :: PyPy
License-File: LICENSE-APACHE
License-File: LICENSE-MIT
Author: Michael Sanders <crates@michaelsande.rs>
Author-email: Michael Sanders <crates@michaelsande.rs>
Requires-Python: >=3.8
